dracor/__init__.py
dracor/dracor.py
dracor-0.0.4.dist-info/LICENSE
dracor-0.0.4.dist-info/METADATA
dracor-0.0.4.dist-info/WHEEL
dracor-0.0.4.dist-info/top_level.txt
dracor-0.0.4.dist-info/RECORD
