Metadata-Version: 2.1
Name: dracor
Version: 0.0.4
Summary: A simple Python library to access the DraCor API.
Author-email: Robert Jäschke <jaeschke@L3S.de>
License: MIT License        
Project-URL: Homepage, https://github.com/weltliteratur/dracor
Project-URL: Bug Tracker, https://github.com/weltliteratur/dracor/issues
Classifier: Programming Language :: Python :: 3
Classifier: License :: OSI Approved :: MIT License
Classifier: Operating System :: OS Independent
Requires-Python: >=3.7
License-File: LICENSE
